{
  "quizId": "affirmation_003",
  "title": "Communication Styles",
  "category": "lighthearted",
  "branch": "lighthearted",
  "description": "How you express yourself and process thoughts",
  "questions": [
    {
      "id": "affirmation_003_q1",
      "text": "I think out loud and process by talking",
      "type": "scale",
      "scaleLabels": ["Strongly Disagree", "Disagree", "Neutral", "Agree", "Strongly Agree"]
    },
    {
      "id": "affirmation_003_q2",
      "text": "I prefer to think things through before sharing my opinion",
      "type": "scale",
      "scaleLabels": ["Strongly Disagree", "Disagree", "Neutral", "Agree", "Strongly Agree"]
    },
    {
      "id": "affirmation_003_q3",
      "text": "I'm comfortable expressing negative emotions directly",
      "type": "scale",
      "scaleLabels": ["Strongly Disagree", "Disagree", "Neutral", "Agree", "Strongly Agree"]
    },
    {
      "id": "affirmation_003_q4",
      "text": "I often hint at what I need rather than stating it clearly",
      "type": "scale",
      "scaleLabels": ["Strongly Disagree", "Disagree", "Neutral", "Agree", "Strongly Agree"]
    },
    {
      "id": "affirmation_003_q5",
      "text": "I feel heard when my partner gives me their full attention",
      "type": "scale",
      "scaleLabels": ["Strongly Disagree", "Disagree", "Neutral", "Agree", "Strongly Agree"]
    }
  ]
}
